pomd/__init__.py
pomd-0.0.1.dist-info/METADATA
pomd-0.0.1.dist-info/WHEEL
pomd-0.0.1.dist-info/top_level.txt
pomd-0.0.1.dist-info/RECORD
