Metadata-Version: 2.1
Name: pomd
Version: 0.0.1
Summary: All POMD modules.
Home-page: https://github.com/SimonRovder/pomd
Author: Simon Rovder
Author-email: simon.rovder@gmail.com
License: UNKNOWN
Platform: UNKNOWN
Classifier: Development Status :: 1 - Planning
Requires-Python: >=3.5
